{
  "slug": "green-shoots-in-an-altered-mobility-landscape-the-way-ahead",
  "title": "Green Shoots in an Altered Mobility Landscape: The Way Ahead",
  "published": true,
  "source_url": "",
  "paper_url": "https://auto.economictimes.indiatimes.com/news/two-wheelers/opinion-green-shoots-in-an-altered-mobility-landscape-the-way-ahead/77758924",
  "summary": {
    "about": "The uneven recovery and longer-term prospects of India’s vehicle market after lockdown.",
    "audience": "Automotive manufacturers, mobility investors and industrial policymakers.",
    "method": "Reviews company sales, industry forecasts, rural demand, emissions rules and electric-vehicle policy.",
    "insights": "Two- and three-wheelers have stronger prospects because of affordability, rural demand, social distancing and EV incentives."
  },
  "placements": [
    {
      "industry": "manufacturing",
      "order": 6,
      "category": "Manufacturing",
      "image": null,
      "image_url": "https://images.unsplash.com/photo-1615829386703-e2bb66a7cb7d?auto=format&fit=crop&w=760&h=430&q=78"
    }
  ]
}
